{
  "User": {
    "id": 1,
    "name": "John Doe"
  },
  "Domains": [
    {
      "id": 1,
      "name": "Domain1"
    },
    {
      "id": 2,
      "name": "Domain2"
    }
  ],
  "DomainDetail": [
    {
      "id": 1,
      "name": "DomainDetail1"
    }
  ],
  "posts": [
    {
      "id": 1,
      "title": "json-server",
      "author": "typicode"
    }
  ],
  "Domain": [
    {
      "id": 1,
      "name": "Domain1",
      "code": 111
    },
    {
      "id": 2,
      "name": "Domain2",
      "code": 222
    },
    {
      "id": 3,
      "name": "Domain3",
      "code": 333
    }
  ],
  "PlanCareEndGoalSummary1": [],
  "PlanCareGoalSummary1": [
    {
      "careGoalName": "careGoal-updated",
      "id": 1
    },
    {
      "careGoalName": "careGoal-updated",
      "id": 2
    },
    {
      "careGoalName": "careGoal-updated",
      "id": 3
    },
    {
      "careGoalName": "careGoal-updated",
      "id": 4
    },
    {
      "careGoalName": "careGoal-updated",
      "id": 5
    },
    {
      "careGoalName": "careGoal-updated",
      "id": 6
    },
    {
      "careGoalName": "somename",
      "id": 7
    },
    {
      "careGoalName": "careGoal-updated",
      "id": 8
    },
    {
      "careGoalName": "somename",
      "id": 9
    },
    {
      "careGoalName": "somename",
      "id": 10
    },
    {
      "careGoalName": "somename",
      "id": 11
    },
    {
      "careGoalName": "careGoal-updated",
      "id": 12
    },
    {
      "careGoalName": "careGoal-updated",
      "id": 13
    },
    {
      "careGoalName": "somename",
      "id": 14
    },
    {
      "careGoalName": "somename",
      "id": 15
    },
    {
      "careGoalName": "somename",
      "id": 16
    },
    {
      "careGoalName": "somename",
      "id": 17
    },
    {
      "careGoalName": "careGoal-updated",
      "id": 18
    },
    {
      "careGoalName": "careGoal-updated",
      "id": 19
    },
    {
      "careGoalName": "careGoal-updated",
      "id": 20
    },
    {
      "careGoalName": "somename",
      "id": 21
    },
    {
      "careGoalName": "somename",
      "id": 22
    },
    {
      "careGoalName": "somename",
      "id": 23
    },
    {
      "careGoalName": "somename",
      "id": 24
    },
    {
      "careGoalName": "somename",
      "id": 26
    },
    {
      "careGoalName": "somename",
      "id": 27
    },
    {
      "careGoalName": "somename",
      "id": 28
    },
    {
      "careGoalName": "somename",
      "id": 29
    },
    {
      "careGoalName": "somename",
      "id": 30
    },
    {
      "careGoalName": "somename",
      "id": 32
    },
    {
      "careGoalName": "careGoal-updated",
      "id": 35
    },
    {
      "careGoalName": "careGoal-updated",
      "id": 39
    },
    {
      "careGoalName": "somename",
      "id": 40
    },
    {
      "careGoalName": "somename",
      "id": 41
    },
    {
      "careGoalName": "somename",
      "id": 44
    },
    {
      "careGoalName": "somename",
      "id": 46
    },
    {
      "careGoalName": "careGoal-updated",
      "id": 47
    },
    {
      "careGoalName": "somename",
      "id": 48
    },
    {
      "careGoalName": "somename",
      "id": 49
    },
    {
      "careGoalName": "somename",
      "id": 53
    },
    {
      "careGoalName": "somename",
      "id": 54
    },
    {
      "careGoalName": "somename",
      "id": 57
    },
    {
      "careGoalName": "somename",
      "id": 61
    },
    {
      "careGoalName": "somename",
      "id": 62
    },
    {
      "careGoalName": "somename",
      "id": 69
    },
    {
      "careGoalName": "careGoal-updated",
      "id": 70
    },
    {
      "careGoalName": "somename",
      "id": 72
    },
    {
      "careGoalName": "somename",
      "id": 74
    },
    {
      "careGoalName": "somename",
      "id": 75
    },
    {
      "careGoalName": "somename",
      "id": 76
    },
    {
      "careGoalName": "somename",
      "id": 77
    },
    {
      "careGoalName": "somename",
      "id": 78
    },
    {
      "careGoalName": "somename",
      "id": 84
    },
    {
      "careGoalName": "somename",
      "id": 85
    },
    {
      "careGoalName": "somename",
      "id": 87
    },
    {
      "careGoalName": "somename",
      "id": 88
    },
    {
      "careGoalName": "somename",
      "id": 89
    },
    {
      "careGoalName": "somename",
      "id": 91
    },
    {
      "careGoalName": "somename",
      "id": 92
    },
    {
      "careGoalName": "somename",
      "id": 94
    },
    {
      "careGoalName": "somename",
      "id": 95
    },
    {
      "careGoalName": "somename",
      "id": 97
    },
    {
      "careGoalName": "somename",
      "id": 104
    },
    {
      "careGoalName": "somename",
      "id": 108
    },
    {
      "careGoalName": "careGoal-updated",
      "id": 109
    },
    {
      "careGoalName": "careGoal-updated",
      "id": 110
    },
    {
      "careGoalName": "somename",
      "id": 112
    }
  ],
  "PlanCareGoalSummary2": [
    {
      "careGoalName": "careGoal-updated",
      "id": 1
    },
    {
      "careGoalName": "careGoal-updated",
      "id": 2
    },
    {
      "careGoalName": "careGoal-updated",
      "id": 3
    },
    {
      "careGoalName": "somename",
      "id": 4
    },
    {
      "careGoalName": "careGoal-updated",
      "id": 5
    },
    {
      "careGoalName": "somename",
      "id": 6
    },
    {
      "careGoalName": "somename",
      "id": 7
    },
    {
      "careGoalName": "careGoal-updated",
      "id": 8
    },
    {
      "careGoalName": "careGoal-updated",
      "id": 9
    },
    {
      "careGoalName": "careGoal-updated",
      "id": 10
    },
    {
      "careGoalName": "somename",
      "id": 11
    },
    {
      "careGoalName": "somename",
      "id": 13
    },
    {
      "careGoalName": "careGoal-updated",
      "id": 14
    },
    {
      "careGoalName": "somename",
      "id": 15
    },
    {
      "careGoalName": "somename",
      "id": 18
    },
    {
      "careGoalName": "somename",
      "id": 19
    },
    {
      "careGoalName": "somename",
      "id": 23
    },
    {
      "careGoalName": "somename",
      "id": 24
    },
    {
      "careGoalName": "somename",
      "id": 25
    },
    {
      "careGoalName": "somename",
      "id": 26
    },
    {
      "careGoalName": "somename",
      "id": 28
    },
    {
      "careGoalName": "careGoal-updated",
      "id": 30
    },
    {
      "careGoalName": "somename",
      "id": 37
    },
    {
      "careGoalName": "somename",
      "id": 39
    },
    {
      "careGoalName": "somename",
      "id": 40
    }
  ],
  "PlanCareGoalSummary3": [
    {
      "careGoalName": "somename",
      "id": 1
    },
    {
      "careGoalName": "somename",
      "id": 2
    },
    {
      "careGoalName": "somename",
      "id": 3
    },
    {
      "careGoalName": "somename",
      "id": 4
    },
    {
      "careGoalName": "somename",
      "id": 5
    },
    {
      "careGoalName": "somename",
      "id": 7
    },
    {
      "careGoalName": "somename",
      "id": 10
    },
    {
      "careGoalName": "somename",
      "id": 11
    },
    {
      "careGoalName": "somename",
      "id": 13
    },
    {
      "careGoalName": "somename",
      "id": 16
    },
    {
      "careGoalName": "somename",
      "id": 17
    },
    {
      "careGoalName": "somename",
      "id": 19
    }
  ],
  "PlanCareEndGoalSummary2": [],
  "PlanCareEndGoalSummary3": [],
  "comments": [
    {
      "id": 1,
      "body": "some comment",
      "postId": 1
    }
  ],
  "profile": {
    "name": "typicode"
  },
  "employees": [
    {
      "id": 1,
      "name": "Pankaj",
      "salary": "10000"
    },
    {
      "name": "David",
      "salary": "5000",
      "id": 2
    }
  ]
}